izumi/__init__.py
izumi/distage/__init__.py
izumi/distage/activation.py
izumi/distage/activation_context.py
izumi/distage/async_locator.py
izumi/distage/dsl.py
izumi/distage/factory.py
izumi/distage/functoid.py
izumi/distage/injector.py
izumi/distage/introspection.py
izumi/distage/lifecycle.py
izumi/distage/locator_base.py
izumi/distage/locator_impl.py
izumi/distage/logger_injection.py
izumi/distage/planner_input.py
izumi/distage/roles.py
izumi/distage/roots.py
izumi/distage/subcontext.py
izumi/distage/tag.py
izumi/distage/model/__init__.py
izumi/distage/model/bindings.py
izumi/distage/model/graph.py
izumi/distage/model/keys.py
izumi/distage/model/operations.py
izumi/distage/model/plan.py
chibi_izumi-0.1.8.dist-info/METADATA
chibi_izumi-0.1.8.dist-info/WHEEL
chibi_izumi-0.1.8.dist-info/licenses/LICENSE
chibi_izumi-0.1.8.dist-info/RECORD
