Metadata-Version: 2.4
Name: chibi-izumi
Version: 0.1.8
Summary: Simplified implementation of Staged Dependency Injection from Scala's distage library of Izumi Project
Project-URL: Homepage, https://github.com/7mind/izumi-chibi-py
Project-URL: Issues, https://github.com/7mind/izumi-chibi-py/issues
Author-email: Pavel Shirshov <pavel@7mind.io>
License-Expression: MIT
License-File: LICENSE
Classifier: Operating System :: OS Independent
Classifier: Programming Language :: Python :: 3
Requires-Python: >=3.12.0
Requires-Dist: beartype>=0.19.0
